maths_add/__init__.py
maths_add/affinity_numbers.py
maths_add/example.cp37-win_amd64.pyd
maths_add/except_error.py
maths_add/factors_and_multiples_numbers.py
maths_add/fibonacci_sequence.py
maths_add/mersenne_numbers.py
maths_add/mingw_setup.py
maths_add/palindromic_numbers.py
maths_add/perfect_numbers.py
maths_add/prime_numbers.py
maths_add/self_powerful_numbers.py
maths_add/setup.py
maths_add/special_numbers.py
maths_add/triangular_numbers.py
maths_add/ugly_numbers.py
maths_add/advanced_computation/__init__.py
maths_add/advanced_computation/logarithm/__init__.py
maths_add/advanced_computation/multiple_powers/__init__.py
maths_add/advanced_computation/power/__init__.py
maths_add/advanced_computation/root/__init__.py
maths_add/complex/__init__.py
maths_add/complex/comp.py
maths_add/computation/__init__.py
maths_add/computation/addtion/__init__.py
maths_add/computation/division/__init__.py
maths_add/computation/multiply/__init__.py
maths_add/computation/reduce/__init__.py
maths_add/decode/AES.py
maths_add/decode/RSA.py
maths_add/decode/SHA_256.py
maths_add/decode/__init__.py
maths_add/fraction/__init__.py
maths_add/fraction/code.py
maths_add/fraction/example_decimal.py
maths_add/fraction/mode.py
maths_add/geometry/__init__.py
maths_add/geometry/decorate.py
maths_add/geometry/three_dimensional_graphics/__init__.py
maths_add/geometry/three_dimensional_graphics/sum_of_edge_Lengths/__init__.py
maths_add/geometry/three_dimensional_graphics/surface_area/__init__.py
maths_add/geometry/three_dimensional_graphics/volume/__init__.py
maths_add/geometry/two_dimensional_graphics/__init__.py
maths_add/geometry/two_dimensional_graphics/area/__init__.py
maths_add/geometry/two_dimensional_graphics/circumference/__init__.py
maths_add/geometry/two_dimensional_graphics/perimeter/__init__.py
maths_add/set/__init__.py
maths_add-2.5.7.dist-info/METADATA
maths_add-2.5.7.dist-info/WHEEL
maths_add-2.5.7.dist-info/top_level.txt
maths_add-2.5.7.dist-info/RECORD
