Metadata-Version: 2.1
Name: maths-add
Version: 2.5.7
Summary: An extended math library
Home-page: https://github.com/fourth-dimensional/maths_add
Author: fourth-dimensional_universe
Author-email: 3817201131@qq.com
License: MIT
Classifier: Programming Language :: Python :: 3.7
Classifier: Programming Language :: Python :: 3.8
Classifier: Programming Language :: Python :: 3.9
Classifier: Programming Language :: Python :: 3.10
Classifier: Programming Language :: Python :: 3.11
Classifier: Programming Language :: Python :: 3.12
Classifier: License :: OSI Approved :: MIT License
Classifier: Operating System :: OS Independent
Requires-Python: >=3.7
Requires-Dist: pycryptodome
Requires-Dist: cryptography
Requires-Dist: sympy
